[
  {
    "anonymous": false,
    "inputs": [
      {
        "indexed": true,
        "internalType": "uint256",
        "name": "rankId",
        "type": "uint256"
      },
      {
        "indexed": true,
        "internalType": "address",
        "name": "recipient",
        "type": "address"
      },
      {
        "indexed": false,
        "internalType": "address",
        "name": "token",
        "type": "address"
      },
      {
        "indexed": false,
        "internalType": "uint256",
        "name": "amount",
        "type": "uint256"
      },
      {
        "indexed": false,
        "internalType": "uint256",
        "name": "timestamp",
        "type": "uint256"
      }
    ],
    "name": "Claimed",
    "type": "event"
  },
  {
    "anonymous": false,
    "inputs": [
      {
        "indexed": false,
        "internalType": "uint8",
        "name": "version",
        "type": "uint8"
      }
    ],
    "name": "Initialized",
    "type": "event"
  },
  {
    "anonymous": false,
    "inputs": [
      {
        "indexed": false,
        "internalType": "address",
        "name": "account",
        "type": "address"
      }
    ],
    "name": "Paused",
    "type": "event"
  },
  {
    "anonymous": false,
    "inputs": [
      {
        "indexed": true,
        "internalType": "bytes32",
        "name": "role",
        "type": "bytes32"
      },
      {
        "indexed": true,
        "internalType": "bytes32",
        "name": "previousAdminRole",
        "type": "bytes32"
      },
      {
        "indexed": true,
        "internalType": "bytes32",
        "name": "newAdminRole",
        "type": "bytes32"
      }
    ],
    "name": "RoleAdminChanged",
    "type": "event"
  },
  {
    "anonymous": false,
    "inputs": [
      {
        "indexed": true,
        "internalType": "bytes32",
        "name": "role",
        "type": "bytes32"
      },
      {
        "indexed": true,
        "internalType": "address",
        "name": "account",
        "type": "address"
      },
      {
        "indexed": true,
        "internalType": "address",
        "name": "sender",
        "type": "address"
      }
    ],
    "name": "RoleGranted",
    "type": "event"
  },
  {
    "anonymous": false,
    "inputs": [
      {
        "indexed": true,
        "internalType": "bytes32",
        "name": "role",
        "type": "bytes32"
      },
      {
        "indexed": true,
        "internalType": "address",
        "name": "account",
        "type": "address"
      },
      {
        "indexed": true,
        "internalType": "address",
        "name": "sender",
        "type": "address"
      }
    ],
    "name": "RoleRevoked",
    "type": "event"
  },
  {
    "anonymous": false,
    "inputs": [
      {
        "indexed": false,
        "internalType": "uint256",
        "name": "season",
        "type": "uint256"
      },
      {
        "indexed": false,
        "internalType": "uint256",
        "name": "duelType",
        "type": "uint256"
      },
      {
        "indexed": false,
        "internalType": "uint256",
        "name": "rank",
        "type": "uint256"
      },
      {
        "indexed": false,
        "internalType": "uint256",
        "name": "rankId",
        "type": "uint256"
      },
      {
        "indexed": false,
        "internalType": "address",
        "name": "token",
        "type": "address"
      },
      {
        "indexed": false,
        "internalType": "uint256",
        "name": "amount",
        "type": "uint256"
      }
    ],
    "name": "SetReward",
    "type": "event"
  },
  {
    "anonymous": false,
    "inputs": [
      {
        "indexed": false,
        "internalType": "address",
        "name": "account",
        "type": "address"
      }
    ],
    "name": "Unpaused",
    "type": "event"
  },
  {
    "inputs": [],
    "name": "DEFAULT_ADMIN_ROLE",
    "outputs": [
      {
        "internalType": "bytes32",
        "name": "",
        "type": "bytes32"
      }
    ],
    "stateMutability": "view",
    "type": "function"
  },
  {
    "inputs": [],
    "name": "MODERATOR_ROLE",
    "outputs": [
      {
        "internalType": "bytes32",
        "name": "",
        "type": "bytes32"
      }
    ],
    "stateMutability": "view",
    "type": "function"
  },
  {
    "inputs": [
      {
        "internalType": "uint256",
        "name": "_season",
        "type": "uint256"
      },
      {
        "internalType": "uint256",
        "name": "_duelType",
        "type": "uint256"
      },
      {
        "internalType": "uint256",
        "name": "_rank",
        "type": "uint256"
      }
    ],
    "name": "_calculateRankId",
    "outputs": [
      {
        "internalType": "uint256",
        "name": "",
        "type": "uint256"
      }
    ],
    "stateMutability": "pure",
    "type": "function"
  },
  {
    "inputs": [
      {
        "internalType": "uint256",
        "name": "_season",
        "type": "uint256"
      },
      {
        "internalType": "uint256",
        "name": "_duelType",
        "type": "uint256"
      },
      {
        "internalType": "uint256",
        "name": "_rank",
        "type": "uint256"
      }
    ],
    "name": "claimReward",
    "outputs": [],
    "stateMutability": "nonpayable",
    "type": "function"
  },
  {
    "inputs": [
      {
        "internalType": "uint256",
        "name": "_season",
        "type": "uint256"
      },
      {
        "internalType": "uint256",
        "name": "_duelType",
        "type": "uint256"
      },
      {
        "internalType": "address",
        "name": "_user",
        "type": "address"
      }
    ],
    "name": "getClaimedRanks",
    "outputs": [
      {
        "internalType": "uint256[]",
        "name": "",
        "type": "uint256[]"
      }
    ],
    "stateMutability": "view",
    "type": "function"
  },
  {
    "inputs": [
      {
        "internalType": "uint256",
        "name": "_season",
        "type": "uint256"
      },
      {
        "internalType": "uint256",
        "name": "_duelType",
        "type": "uint256"
      },
      {
        "internalType": "uint256",
        "name": "_rank",
        "type": "uint256"
      }
    ],
    "name": "getRewards",
    "outputs": [
      {
        "components": [
          {
            "internalType": "address",
            "name": "tokenAddress",
            "type": "address"
          },
          {
            "internalType": "uint256",
            "name": "amount",
            "type": "uint256"
          }
        ],
        "internalType": "struct DuelRankClaim.RankReward[]",
        "name": "",
        "type": "tuple[]"
      }
    ],
    "stateMutability": "view",
    "type": "function"
  },
  {
    "inputs": [
      {
        "internalType": "uint256",
        "name": "_season",
        "type": "uint256"
      },
      {
        "internalType": "uint256",
        "name": "_duelType",
        "type": "uint256"
      }
    ],
    "name": "getRewardsForSeasonAndDuelType",
    "outputs": [
      {
        "components": [
          {
            "internalType": "address",
            "name": "tokenAddress",
            "type": "address"
          },
          {
            "internalType": "uint256",
            "name": "amount",
            "type": "uint256"
          }
        ],
        "internalType": "struct DuelRankClaim.RankReward[][]",
        "name": "",
        "type": "tuple[][]"
      }
    ],
    "stateMutability": "view",
    "type": "function"
  },
  {
    "inputs": [
      {
        "internalType": "bytes32",
        "name": "role",
        "type": "bytes32"
      }
    ],
    "name": "getRoleAdmin",
    "outputs": [
      {
        "internalType": "bytes32",
        "name": "",
        "type": "bytes32"
      }
    ],
    "stateMutability": "view",
    "type": "function"
  },
  {
    "inputs": [
      {
        "internalType": "address",
        "name": "_player",
        "type": "address"
      },
      {
        "internalType": "uint256",
        "name": "_season",
        "type": "uint256"
      },
      {
        "internalType": "uint256",
        "name": "_duelType",
        "type": "uint256"
      }
    ],
    "name": "getSeasonInfo",
    "outputs": [
      {
        "internalType": "uint64",
        "name": "score",
        "type": "uint64"
      },
      {
        "internalType": "uint256",
        "name": "rank",
        "type": "uint256"
      },
      {
        "internalType": "uint16[]",
        "name": "ranks",
        "type": "uint16[]"
      },
      {
        "internalType": "uint256[]",
        "name": "claimedRanks",
        "type": "uint256[]"
      },
      {
        "components": [
          {
            "internalType": "address",
            "name": "tokenAddress",
            "type": "address"
          },
          {
            "internalType": "uint256",
            "name": "amount",
            "type": "uint256"
          }
        ],
        "internalType": "struct DuelRankClaim.RankReward[][]",
        "name": "rewards",
        "type": "tuple[][]"
      },
      {
        "internalType": "uint256",
        "name": "startTime",
        "type": "uint256"
      },
      {
        "internalType": "uint256",
        "name": "duration",
        "type": "uint256"
      }
    ],
    "stateMutability": "view",
    "type": "function"
  },
  {
    "inputs": [
      {
        "internalType": "uint256",
        "name": "_season",
        "type": "uint256"
      },
      {
        "internalType": "uint256",
        "name": "_duelType",
        "type": "uint256"
      }
    ],
    "name": "getSeasonRankRequirements",
    "outputs": [
      {
        "internalType": "uint16[]",
        "name": "",
        "type": "uint16[]"
      }
    ],
    "stateMutability": "view",
    "type": "function"
  },
  {
    "inputs": [
      {
        "internalType": "bytes32",
        "name": "role",
        "type": "bytes32"
      },
      {
        "internalType": "address",
        "name": "account",
        "type": "address"
      }
    ],
    "name": "grantRole",
    "outputs": [],
    "stateMutability": "nonpayable",
    "type": "function"
  },
  {
    "inputs": [
      {
        "internalType": "bytes32",
        "name": "role",
        "type": "bytes32"
      },
      {
        "internalType": "address",
        "name": "account",
        "type": "address"
      }
    ],
    "name": "hasRole",
    "outputs": [
      {
        "internalType": "bool",
        "name": "",
        "type": "bool"
      }
    ],
    "stateMutability": "view",
    "type": "function"
  },
  {
    "inputs": [
      {
        "internalType": "address",
        "name": "_itemMinter",
        "type": "address"
      }
    ],
    "name": "initialize",
    "outputs": [],
    "stateMutability": "nonpayable",
    "type": "function"
  },
  {
    "inputs": [],
    "name": "pause",
    "outputs": [],
    "stateMutability": "nonpayable",
    "type": "function"
  },
  {
    "inputs": [],
    "name": "paused",
    "outputs": [
      {
        "internalType": "bool",
        "name": "",
        "type": "bool"
      }
    ],
    "stateMutability": "view",
    "type": "function"
  },
  {
    "inputs": [
      {
        "internalType": "uint256",
        "name": "",
        "type": "uint256"
      },
      {
        "internalType": "uint256",
        "name": "",
        "type": "uint256"
      }
    ],
    "name": "rankRewards",
    "outputs": [
      {
        "internalType": "address",
        "name": "tokenAddress",
        "type": "address"
      },
      {
        "internalType": "uint256",
        "name": "amount",
        "type": "uint256"
      }
    ],
    "stateMutability": "view",
    "type": "function"
  },
  {
    "inputs": [
      {
        "internalType": "bytes32",
        "name": "role",
        "type": "bytes32"
      },
      {
        "internalType": "address",
        "name": "account",
        "type": "address"
      }
    ],
    "name": "renounceRole",
    "outputs": [],
    "stateMutability": "nonpayable",
    "type": "function"
  },
  {
    "inputs": [
      {
        "internalType": "bytes32",
        "name": "role",
        "type": "bytes32"
      },
      {
        "internalType": "address",
        "name": "account",
        "type": "address"
      }
    ],
    "name": "revokeRole",
    "outputs": [],
    "stateMutability": "nonpayable",
    "type": "function"
  },
  {
    "inputs": [
      {
        "internalType": "uint256",
        "name": "_season",
        "type": "uint256"
      },
      {
        "internalType": "address",
        "name": "_duelContract",
        "type": "address"
      }
    ],
    "name": "setDuelContract",
    "outputs": [],
    "stateMutability": "nonpayable",
    "type": "function"
  },
  {
    "inputs": [
      {
        "internalType": "address",
        "name": "_itemMinter",
        "type": "address"
      }
    ],
    "name": "setItemMinter",
    "outputs": [],
    "stateMutability": "nonpayable",
    "type": "function"
  },
  {
    "inputs": [
      {
        "internalType": "uint256",
        "name": "_season",
        "type": "uint256"
      },
      {
        "internalType": "uint256",
        "name": "_duelType",
        "type": "uint256"
      },
      {
        "internalType": "uint256",
        "name": "_rank",
        "type": "uint256"
      },
      {
        "internalType": "address[]",
        "name": "_tokenAddresses",
        "type": "address[]"
      },
      {
        "internalType": "uint256[]",
        "name": "_amounts",
        "type": "uint256[]"
      }
    ],
    "name": "setRankRewards",
    "outputs": [],
    "stateMutability": "nonpayable",
    "type": "function"
  },
  {
    "inputs": [
      {
        "internalType": "bytes4",
        "name": "interfaceId",
        "type": "bytes4"
      }
    ],
    "name": "supportsInterface",
    "outputs": [
      {
        "internalType": "bool",
        "name": "",
        "type": "bool"
      }
    ],
    "stateMutability": "view",
    "type": "function"
  },
  {
    "inputs": [],
    "name": "unpause",
    "outputs": [],
    "stateMutability": "nonpayable",
    "type": "function"
  },
  {
    "inputs": [
      {
        "internalType": "uint256",
        "name": "",
        "type": "uint256"
      },
      {
        "internalType": "address",
        "name": "",
        "type": "address"
      }
    ],
    "name": "userRankClaims",
    "outputs": [
      {
        "internalType": "uint256",
        "name": "",
        "type": "uint256"
      }
    ],
    "stateMutability": "view",
    "type": "function"
  }
]